{
  "collectionName": "components_distribution_heroes",
  "info": {
    "displayName": "Hero",
    "description": ""
  },
  "options": {},
  "attributes": {
    "title": { "type": "string" },
    "subtitle": { "type": "string" },
    "introText": { "type": "text" },
    "description": { "type": "text" },
    "primaryCTA": { "type": "string" },
    "secondaryCTA": { "type": "string" },
    "features": {
      "type": "component",
      "repeatable": true,
      "component": "distribution.feature"
    }
  }
}
